{
  "schema": "v1",
  "enabled": true,
  "name": "instinct",
  "anchor": {
    "Screen": "BottomCenter"
  },
  "pos": [
    0.0,
    0.0
  ],
  "opacity": 1.0,
  "trigger": {
    "source": "Inherit",
    "threshold": {
      "threshold_type": "Always",
      "amount_type": "Intensity"
    }
  },
  "filter": {
    "player": {
      "combat": null,
      "specs": [],
      "weapons": [],
      "traits": [],
      "mounts": []
    },
    "map": {
      "category": [
        "PvE",
        "Instance",
        "Other"
      ],
      "whitelist": true,
      "ids": []
    }
  },
  "animation": null,
  "layer": 0,
  "elements": [
    {
      "enabled": true,
      "name": "vindicator",
      "anchor": "Parent",
      "pos": [
        0.0,
        -199.0
      ],
      "opacity": 1.0,
      "trigger": {
        "source": "Inherit",
        "threshold": {
          "threshold_type": "Always",
          "amount_type": "Intensity"
        }
      },
      "filter": {
        "player": {
          "combat": null,
          "specs": [
            "Vindicator"
          ],
          "weapons": [],
          "traits": [],
          "mounts": []
        },
        "map": {
          "category": [],
          "whitelist": true,
          "ids": []
        }
      },
      "animation": null,
      "type": "Group",
      "members": [
        {
          "enabled": true,
          "name": "level-0",
          "anchor": "Parent",
          "pos": [
            0.0,
            0.0
          ],
          "opacity": 1.0,
          "trigger": {
            "source": "Always",
            "threshold": {
              "threshold_type": "Always",
              "amount_type": "Intensity"
            }
          },
          "filter": {
            "player": {
              "combat": null,
              "specs": [],
              "weapons": [],
              "traits": [],
              "mounts": []
            },
            "map": {
              "category": [],
              "whitelist": true,
              "ids": []
            }
          },
          "animation": null,
          "type": "Icon",
          "icon": {
            "File": "instinct\\vindi\\level-0.png"
          },
          "tint": [
            1.0,
            1.0,
            1.0,
            1.0
          ],
          "zoom": 1.0,
          "round": 0.0,
          "border_size": 0.0,
          "border_color": [
            0.0,
            0.0,
            0.0,
            1.0
          ],
          "conditions": [],
          "duration_bar": false,
          "duration_text": false,
          "stacks_text": false,
          "size": [
            172.0,
            152.0
          ]
        },
        {
          "enabled": true,
          "name": "endurance",
          "anchor": "Parent",
          "pos": [
            0.0,
            0.0
          ],
          "opacity": 1.0,
          "trigger": {
            "source": "Endurance",
            "threshold": {
              "threshold_type": "Always",
              "amount_type": "Intensity"
            }
          },
          "filter": {
            "player": {
              "combat": true,
              "specs": [],
              "weapons": [],
              "traits": [],
              "mounts": []
            },
            "map": {
              "category": [],
              "whitelist": true,
              "ids": []
            }
          },
          "animation": null,
          "type": "Group",
          "members": [
            {
              "enabled": true,
              "name": "level-0.5 - 20",
              "anchor": "Parent",
              "pos": [
                0.0,
                0.0
              ],
              "opacity": 1.0,
              "trigger": {
                "source": "Inherit",
                "threshold": {
                  "threshold_type": {
                    "Above": 20.0
                  },
                  "amount_type": "Intensity"
                }
              },
              "filter": {
                "player": {
                  "combat": null,
                  "specs": [],
                  "weapons": [],
                  "traits": [],
                  "mounts": []
                },
                "map": {
                  "category": [],
                  "whitelist": true,
                  "ids": []
                }
              },
              "animation": null,
              "type": "Icon",
              "icon": {
                "File": "instinct\\vindi\\swoosh.png"
              },
              "tint": [
                1.0,
                1.0,
                1.0,
                1.0
              ],
              "zoom": 1.0,
              "round": 0.0,
              "border_size": 0.0,
              "border_color": [
                0.0,
                0.0,
                0.0,
                1.0
              ],
              "conditions": [],
              "duration_bar": false,
              "duration_text": false,
              "stacks_text": false,
              "size": [
                172.0,
                152.0
              ]
            },
            {
              "enabled": true,
              "name": "level-1 - 45",
              "anchor": "Parent",
              "pos": [
                0.0,
                0.0
              ],
              "opacity": 1.0,
              "trigger": {
                "source": "Inherit",
                "threshold": {
                  "threshold_type": {
                    "Above": 45.0
                  },
                  "amount_type": "Intensity"
                }
              },
              "filter": {
                "player": {
                  "combat": null,
                  "specs": [],
                  "weapons": [],
                  "traits": [],
                  "mounts": []
                },
                "map": {
                  "category": [],
                  "whitelist": true,
                  "ids": []
                }
              },
              "animation": null,
              "type": "Icon",
              "icon": {
                "File": "instinct\\vindi\\level-1.png"
              },
              "tint": [
                1.0,
                1.0,
                1.0,
                1.0
              ],
              "zoom": 1.0,
              "round": 0.0,
              "border_size": 0.0,
              "border_color": [
                0.0,
                0.0,
                0.0,
                1.0
              ],
              "conditions": [],
              "duration_bar": false,
              "duration_text": false,
              "stacks_text": false,
              "size": [
                172.0,
                152.0
              ]
            },
            {
              "enabled": true,
              "name": "level-2 - 90",
              "anchor": "Parent",
              "pos": [
                0.0,
                0.0
              ],
              "opacity": 1.0,
              "trigger": {
                "source": "Inherit",
                "threshold": {
                  "threshold_type": {
                    "Above": 90.0
                  },
                  "amount_type": "Intensity"
                }
              },
              "filter": {
                "player": {
                  "combat": null,
                  "specs": [],
                  "weapons": [],
                  "traits": [],
                  "mounts": []
                },
                "map": {
                  "category": [],
                  "whitelist": true,
                  "ids": []
                }
              },
              "animation": null,
              "type": "Icon",
              "icon": {
                "File": "instinct\\vindi\\level-2.png"
              },
              "tint": [
                1.0,
                1.0,
                1.0,
                1.0
              ],
              "zoom": 1.0,
              "round": 0.0,
              "border_size": 0.0,
              "border_color": [
                0.0,
                0.0,
                0.0,
                1.0
              ],
              "conditions": [],
              "duration_bar": false,
              "duration_text": false,
              "stacks_text": false,
              "size": [
                172.0,
                152.0
              ]
            },
            {
              "enabled": true,
              "name": "level-max - 100",
              "anchor": "Parent",
              "pos": [
                0.0,
                0.0
              ],
              "opacity": 1.0,
              "trigger": {
                "source": "Inherit",
                "threshold": {
                  "threshold_type": {
                    "Exact": 100.0
                  },
                  "amount_type": "Intensity"
                }
              },
              "filter": {
                "player": {
                  "combat": null,
                  "specs": [],
                  "weapons": [],
                  "traits": [],
                  "mounts": []
                },
                "map": {
                  "category": [],
                  "whitelist": true,
                  "ids": []
                }
              },
              "animation": {
                "kind": "Pulse",
                "period": 800
              },
              "type": "Icon",
              "icon": {
                "File": "instinct\\vindi\\exclamation.png"
              },
              "tint": [
                1.0,
                1.0,
                1.0,
                1.0
              ],
              "zoom": 1.0,
              "round": 0.0,
              "border_size": 0.0,
              "border_color": [
                0.0,
                0.0,
                0.0,
                1.0
              ],
              "conditions": [],
              "duration_bar": false,
              "duration_text": false,
              "stacks_text": false,
              "size": [
                172.0,
                152.0
              ]
            }
          ]
        },
        {
          "enabled": true,
          "name": "reavers-curse",
          "anchor": "Parent",
          "pos": [
            0.0,
            0.0
          ],
          "opacity": 1.0,
          "trigger": {
            "source": {
              "Buff": [
                71983
              ]
            },
            "threshold": {
              "threshold_type": "Always",
              "amount_type": "Intensity"
            }
          },
          "filter": {
            "player": {
              "combat": null,
              "specs": [],
              "weapons": [],
              "traits": [],
              "mounts": []
            },
            "map": {
              "category": [],
              "whitelist": true,
              "ids": []
            }
          },
          "animation": null,
          "type": "Group",
          "members": [
            {
              "enabled": true,
              "name": "indicator",
              "anchor": "Parent",
              "pos": [
                0.0,
                0.0
              ],
              "opacity": 1.0,
              "trigger": {
                "source": "Inherit",
                "threshold": {
                  "threshold_type": "Present",
                  "amount_type": "Intensity"
                }
              },
              "filter": {
                "player": {
                  "combat": null,
                  "specs": [],
                  "weapons": [],
                  "traits": [],
                  "mounts": []
                },
                "map": {
                  "category": [],
                  "whitelist": true,
                  "ids": []
                }
              },
              "animation": null,
              "type": "Icon",
              "icon": {
                "File": "instinct\\vindi\\flames.png"
              },
              "tint": [
                1.0,
                1.0,
                1.0,
                1.0
              ],
              "zoom": 1.0,
              "round": 0.0,
              "border_size": 0.0,
              "border_color": [
                0.0,
                0.0,
                0.0,
                1.0
              ],
              "conditions": [],
              "duration_bar": false,
              "duration_text": false,
              "stacks_text": false,
              "size": [
                172.0,
                152.0
              ]
            },
            {
              "enabled": true,
              "name": "duration",
              "anchor": "Parent",
              "pos": [
                -79.0,
                54.0
              ],
              "opacity": 1.0,
              "trigger": {
                "source": "Inherit",
                "threshold": {
                  "threshold_type": "Always",
                  "amount_type": "Intensity"
                }
              },
              "filter": {
                "player": {
                  "combat": null,
                  "specs": [],
                  "weapons": [],
                  "traits": [],
                  "mounts": []
                },
                "map": {
                  "category": [],
                  "whitelist": true,
                  "ids": []
                }
              },
              "animation": null,
              "type": "Bar",
              "progress_kind": "Duration",
              "max": 25.0,
              "lower_bound": 0.0,
              "upper_bound": 1.0,
              "fill": [
                0.99999,
                1.0,
                0.99999,
                1.0
              ],
              "background": [
                0.0,
                0.0,
                0.0,
                0.38323355
              ],
              "border_size": 1.0,
              "border_color": [
                0.0,
                0.0,
                0.0,
                1.0
              ],
              "tick_size": 1.0,
              "tick_color": [
                0.0,
                0.0,
                0.0,
                1.0
              ],
              "conditions": [],
              "size": [
                6.0,
                36.0
              ],
              "align": "Up",
              "direction": "Up",
              "tick_unit": "Percent",
              "ticks": []
            }
          ]
        }
      ]
    },
    {
      "enabled": true,
      "name": "willbender",
      "anchor": "Parent",
      "pos": [
        0.0,
        -174.0
      ],
      "opacity": 1.0,
      "trigger": {
        "source": "Inherit",
        "threshold": {
          "threshold_type": "Always",
          "amount_type": "Intensity"
        }
      },
      "filter": {
        "player": {
          "combat": null,
          "specs": [
            "Willbender"
          ],
          "weapons": [],
          "traits": [],
          "mounts": []
        },
        "map": {
          "category": [],
          "whitelist": true,
          "ids": []
        }
      },
      "animation": null,
      "type": "Group",
      "members": [
        {
          "enabled": true,
          "name": "justice",
          "anchor": "Parent",
          "pos": [
            -270.0,
            0.0
          ],
          "opacity": 1.0,
          "trigger": {
            "source": {
              "Buff": [
                62529
              ]
            },
            "threshold": {
              "threshold_type": "Always",
              "amount_type": "Intensity"
            }
          },
          "filter": {
            "player": {
              "combat": null,
              "specs": [],
              "weapons": [],
              "traits": [],
              "mounts": []
            },
            "map": {
              "category": [],
              "whitelist": true,
              "ids": []
            }
          },
          "animation": null,
          "type": "Group",
          "members": [
            {
              "enabled": true,
              "name": "duration",
              "anchor": "Parent",
              "pos": [
                0.0,
                0.0
              ],
              "opacity": 1.0,
              "trigger": {
                "source": "Inherit",
                "threshold": {
                  "threshold_type": "Always",
                  "amount_type": "Intensity"
                }
              },
              "filter": {
                "player": {
                  "combat": null,
                  "specs": [],
                  "weapons": [],
                  "traits": [],
                  "mounts": []
                },
                "map": {
                  "category": [],
                  "whitelist": true,
                  "ids": []
                }
              },
              "animation": null,
              "type": "Bar",
              "progress_kind": "Duration",
              "max": 25.0,
              "lower_bound": 0.0,
              "upper_bound": 1.0,
              "fill": [
                0.99999,
                1.0,
                0.99999,
                1.0
              ],
              "background": [
                0.0,
                0.0,
                0.0,
                0.25149703
              ],
              "border_size": 1.0,
              "border_color": [
                0.0,
                0.0,
                0.0,
                1.0
              ],
              "tick_size": 1.0,
              "tick_color": [
                0.0,
                0.0,
                0.0,
                1.0
              ],
              "conditions": [],
              "size": [
                49.0,
                6.0
              ],
              "align": "Right",
              "direction": "Right",
              "tick_unit": "Percent",
              "ticks": []
            },
            {
              "enabled": true,
              "name": "off",
              "anchor": "Parent",
              "pos": [
                25.0,
                -29.0
              ],
              "opacity": 1.0,
              "trigger": {
                "source": "Inherit",
                "threshold": {
                  "threshold_type": "Always",
                  "amount_type": "Intensity"
                }
              },
              "filter": {
                "player": {
                  "combat": null,
                  "specs": [],
                  "weapons": [],
                  "traits": [],
                  "mounts": []
                },
                "map": {
                  "category": [],
                  "whitelist": true,
                  "ids": []
                }
              },
              "animation": null,
              "type": "Icon",
              "icon": {
                "File": "instinct\\willbender\\justice-off.png"
              },
              "tint": [
                1.0,
                1.0,
                1.0,
                1.0
              ],
              "zoom": 1.0,
              "round": 0.0,
              "border_size": 0.0,
              "border_color": [
                0.0,
                0.0,
                0.0,
                1.0
              ],
              "conditions": [],
              "duration_bar": false,
              "duration_text": false,
              "stacks_text": false,
              "size": [
                44.0,
                44.0
              ]
            },
            {
              "enabled": true,
              "name": "on",
              "anchor": "Parent",
              "pos": [
                25.0,
                -29.0
              ],
              "opacity": 1.0,
              "trigger": {
                "source": "Inherit",
                "threshold": {
                  "threshold_type": "Present",
                  "amount_type": "Intensity"
                }
              },
              "filter": {
                "player": {
                  "combat": null,
                  "specs": [],
                  "weapons": [],
                  "traits": [],
                  "mounts": []
                },
                "map": {
                  "category": [],
                  "whitelist": true,
                  "ids": []
                }
              },
              "animation": null,
              "type": "Icon",
              "icon": {
                "File": "instinct\\willbender\\justice-on.png"
              },
              "tint": [
                1.0,
                1.0,
                1.0,
                1.0
              ],
              "zoom": 1.0,
              "round": 0.0,
              "border_size": 0.0,
              "border_color": [
                0.0,
                0.0,
                0.0,
                1.0
              ],
              "conditions": [],
              "duration_bar": false,
              "duration_text": false,
              "stacks_text": false,
              "size": [
                44.0,
                44.0
              ]
            }
          ]
        },
        {
          "enabled": true,
          "name": "flowing-resolve",
          "anchor": "Parent",
          "pos": [
            -220.0,
            0.0
          ],
          "opacity": 1.0,
          "trigger": {
            "source": {
              "Buff": [
                62632
              ]
            },
            "threshold": {
              "threshold_type": "Always",
              "amount_type": "Intensity"
            }
          },
          "filter": {
            "player": {
              "combat": null,
              "specs": [],
              "weapons": [],
              "traits": [],
              "mounts": []
            },
            "map": {
              "category": [],
              "whitelist": true,
              "ids": []
            }
          },
          "animation": null,
          "type": "Group",
          "members": [
            {
              "enabled": true,
              "name": "duration",
              "anchor": "Parent",
              "pos": [
                0.0,
                0.0
              ],
              "opacity": 1.0,
              "trigger": {
                "source": "Inherit",
                "threshold": {
                  "threshold_type": "Always",
                  "amount_type": "Intensity"
                }
              },
              "filter": {
                "player": {
                  "combat": null,
                  "specs": [],
                  "weapons": [],
                  "traits": [],
                  "mounts": []
                },
                "map": {
                  "category": [],
                  "whitelist": true,
                  "ids": []
                }
              },
              "animation": null,
              "type": "Bar",
              "progress_kind": "Duration",
              "max": 25.0,
              "lower_bound": 0.0,
              "upper_bound": 1.0,
              "fill": [
                0.99999,
                1.0,
                0.99999,
                1.0
              ],
              "background": [
                0.0,
                0.0,
                0.0,
                0.25149703
              ],
              "border_size": 1.0,
              "border_color": [
                0.0,
                0.0,
                0.0,
                1.0
              ],
              "tick_size": 1.0,
              "tick_color": [
                0.0,
                0.0,
                0.0,
                1.0
              ],
              "conditions": [],
              "size": [
                49.0,
                6.0
              ],
              "align": "Right",
              "direction": "Right",
              "tick_unit": "Percent",
              "ticks": []
            },
            {
              "enabled": true,
              "name": "off",
              "anchor": "Parent",
              "pos": [
                25.0,
                -29.0
              ],
              "opacity": 1.0,
              "trigger": {
                "source": "Inherit",
                "threshold": {
                  "threshold_type": "Always",
                  "amount_type": "Intensity"
                }
              },
              "filter": {
                "player": {
                  "combat": null,
                  "specs": [],
                  "weapons": [],
                  "traits": [],
                  "mounts": []
                },
                "map": {
                  "category": [],
                  "whitelist": true,
                  "ids": []
                }
              },
              "animation": null,
              "type": "Icon",
              "icon": {
                "File": "instinct\\willbender\\resolve-off.png"
              },
              "tint": [
                1.0,
                1.0,
                1.0,
                1.0
              ],
              "zoom": 1.0,
              "round": 0.0,
              "border_size": 0.0,
              "border_color": [
                0.0,
                0.0,
                0.0,
                1.0
              ],
              "conditions": [],
              "duration_bar": false,
              "duration_text": false,
              "stacks_text": false,
              "size": [
                44.0,
                44.0
              ]
            },
            {
              "enabled": true,
              "name": "on",
              "anchor": "Parent",
              "pos": [
                25.0,
                -29.0
              ],
              "opacity": 1.0,
              "trigger": {
                "source": "Inherit",
                "threshold": {
                  "threshold_type": "Present",
                  "amount_type": "Intensity"
                }
              },
              "filter": {
                "player": {
                  "combat": null,
                  "specs": [],
                  "weapons": [],
                  "traits": [],
                  "mounts": []
                },
                "map": {
                  "category": [],
                  "whitelist": true,
                  "ids": []
                }
              },
              "animation": null,
              "type": "Icon",
              "icon": {
                "File": "instinct\\willbender\\resolve-on.png"
              },
              "tint": [
                1.0,
                1.0,
                1.0,
                1.0
              ],
              "zoom": 1.0,
              "round": 0.0,
              "border_size": 0.0,
              "border_color": [
                0.0,
                0.0,
                0.0,
                1.0
              ],
              "conditions": [],
              "duration_bar": false,
              "duration_text": false,
              "stacks_text": false,
              "size": [
                44.0,
                44.0
              ]
            }
          ]
        },
        {
          "enabled": true,
          "name": "crashing-courage",
          "anchor": "Parent",
          "pos": [
            -170.0,
            0.0
          ],
          "opacity": 1.0,
          "trigger": {
            "source": {
              "Buff": [
                62615
              ]
            },
            "threshold": {
              "threshold_type": "Always",
              "amount_type": "Intensity"
            }
          },
          "filter": {
            "player": {
              "combat": null,
              "specs": [],
              "weapons": [],
              "traits": [],
              "mounts": []
            },
            "map": {
              "category": [],
              "whitelist": true,
              "ids": []
            }
          },
          "animation": null,
          "type": "Group",
          "members": [
            {
              "enabled": true,
              "name": "duration",
              "anchor": "Parent",
              "pos": [
                0.0,
                0.0
              ],
              "opacity": 1.0,
              "trigger": {
                "source": "Inherit",
                "threshold": {
                  "threshold_type": "Always",
                  "amount_type": "Intensity"
                }
              },
              "filter": {
                "player": {
                  "combat": null,
                  "specs": [],
                  "weapons": [],
                  "traits": [],
                  "mounts": []
                },
                "map": {
                  "category": [],
                  "whitelist": true,
                  "ids": []
                }
              },
              "animation": null,
              "type": "Bar",
              "progress_kind": "Duration",
              "max": 25.0,
              "lower_bound": 0.0,
              "upper_bound": 1.0,
              "fill": [
                0.99999,
                1.0,
                0.99999,
                1.0
              ],
              "background": [
                0.0,
                0.0,
                0.0,
                0.25149703
              ],
              "border_size": 1.0,
              "border_color": [
                0.0,
                0.0,
                0.0,
                1.0
              ],
              "tick_size": 1.0,
              "tick_color": [
                0.0,
                0.0,
                0.0,
                1.0
              ],
              "conditions": [],
              "size": [
                50.0,
                6.0
              ],
              "align": "Right",
              "direction": "Right",
              "tick_unit": "Percent",
              "ticks": []
            },
            {
              "enabled": true,
              "name": "off",
              "anchor": "Parent",
              "pos": [
                25.0,
                -29.0
              ],
              "opacity": 1.0,
              "trigger": {
                "source": "Inherit",
                "threshold": {
                  "threshold_type": "Always",
                  "amount_type": "Intensity"
                }
              },
              "filter": {
                "player": {
                  "combat": null,
                  "specs": [],
                  "weapons": [],
                  "traits": [],
                  "mounts": []
                },
                "map": {
                  "category": [],
                  "whitelist": true,
                  "ids": []
                }
              },
              "animation": null,
              "type": "Icon",
              "icon": {
                "File": "instinct\\willbender\\courage-off.png"
              },
              "tint": [
                1.0,
                1.0,
                1.0,
                1.0
              ],
              "zoom": 1.0,
              "round": 0.0,
              "border_size": 0.0,
              "border_color": [
                0.0,
                0.0,
                0.0,
                1.0
              ],
              "conditions": [],
              "duration_bar": false,
              "duration_text": false,
              "stacks_text": false,
              "size": [
                44.0,
                44.0
              ]
            },
            {
              "enabled": true,
              "name": "on",
              "anchor": "Parent",
              "pos": [
                25.0,
                -29.0
              ],
              "opacity": 1.0,
              "trigger": {
                "source": "Inherit",
                "threshold": {
                  "threshold_type": "Present",
                  "amount_type": "Intensity"
                }
              },
              "filter": {
                "player": {
                  "combat": null,
                  "specs": [],
                  "weapons": [],
                  "traits": [],
                  "mounts": []
                },
                "map": {
                  "category": [],
                  "whitelist": true,
                  "ids": []
                }
              },
              "animation": null,
              "type": "Icon",
              "icon": {
                "File": "instinct\\willbender\\courage-on.png"
              },
              "tint": [
                1.0,
                1.0,
                1.0,
                1.0
              ],
              "zoom": 1.0,
              "round": 0.0,
              "border_size": 0.0,
              "border_color": [
                0.0,
                0.0,
                0.0,
                1.0
              ],
              "conditions": [],
              "duration_bar": false,
              "duration_text": false,
              "stacks_text": false,
              "size": [
                44.0,
                44.0
              ]
            }
          ]
        }
      ]
    },
    {
      "enabled": true,
      "name": "berserker",
      "anchor": "Parent",
      "pos": [
        0.0,
        -168.0
      ],
      "opacity": 1.0,
      "trigger": {
        "source": "Inherit",
        "threshold": {
          "threshold_type": "Always",
          "amount_type": "Intensity"
        }
      },
      "filter": {
        "player": {
          "combat": null,
          "specs": [
            "Berserker"
          ],
          "weapons": [],
          "traits": [],
          "mounts": []
        },
        "map": {
          "category": [],
          "whitelist": true,
          "ids": []
        }
      },
      "animation": null,
      "type": "Group",
      "members": [
        {
          "enabled": true,
          "name": "berserk",
          "anchor": "Parent",
          "pos": [
            -138.0,
            23.0
          ],
          "opacity": 1.0,
          "trigger": {
            "source": {
              "Buff": [
                29502
              ]
            },
            "threshold": {
              "threshold_type": "Always",
              "amount_type": "Intensity"
            }
          },
          "filter": {
            "player": {
              "combat": null,
              "specs": [],
              "weapons": [],
              "traits": [],
              "mounts": []
            },
            "map": {
              "category": [],
              "whitelist": true,
              "ids": []
            }
          },
          "animation": null,
          "type": "Group",
          "members": [
            {
              "enabled": true,
              "name": "bg",
              "anchor": "Parent",
              "pos": [
                -138.0,
                -29.0
              ],
              "opacity": 1.0,
              "trigger": {
                "source": "Inherit",
                "threshold": {
                  "threshold_type": "Present",
                  "amount_type": "Intensity"
                }
              },
              "filter": {
                "player": {
                  "combat": null,
                  "specs": [],
                  "weapons": [],
                  "traits": [],
                  "mounts": []
                },
                "map": {
                  "category": [],
                  "whitelist": true,
                  "ids": []
                }
              },
              "animation": null,
              "type": "Group",
              "members": [
                {
                  "enabled": true,
                  "name": "bg",
                  "anchor": "Parent",
                  "pos": [
                    0.0,
                    0.0
                  ],
                  "opacity": 1.0,
                  "trigger": {
                    "source": "Inherit",
                    "threshold": {
                      "threshold_type": "Always",
                      "amount_type": "Intensity"
                    }
                  },
                  "filter": {
                    "player": {
                      "combat": null,
                      "specs": [],
                      "weapons": [],
                      "traits": [],
                      "mounts": []
                    },
                    "map": {
                      "category": [],
                      "whitelist": true,
                      "ids": []
                    }
                  },
                  "animation": null,
                  "type": "Icon",
                  "icon": {
                    "File": "instinct\\berserker\\bg1.png"
                  },
                  "tint": [
                    1.0,
                    1.0,
                    1.0,
                    1.0
                  ],
                  "zoom": 1.0,
                  "round": 0.0,
                  "border_size": 0.0,
                  "border_color": [
                    0.0,
                    0.0,
                    0.0,
                    1.0
                  ],
                  "conditions": [],
                  "duration_bar": false,
                  "duration_text": false,
                  "stacks_text": false,
                  "size": [
                    276.0,
                    76.0
                  ]
                },
                {
                  "enabled": true,
                  "name": "icon",
                  "anchor": "Parent",
                  "pos": [
                    0.0,
                    0.0
                  ],
                  "opacity": 1.0,
                  "trigger": {
                    "source": "Inherit",
                    "threshold": {
                      "threshold_type": "Always",
                      "amount_type": "Intensity"
                    }
                  },
                  "filter": {
                    "player": {
                      "combat": null,
                      "specs": [],
                      "weapons": [],
                      "traits": [],
                      "mounts": []
                    },
                    "map": {
                      "category": [],
                      "whitelist": true,
                      "ids": []
                    }
                  },
                  "animation": null,
                  "type": "Icon",
                  "icon": {
                    "File": "instinct\\berserker\\berserk2.png"
                  },
                  "tint": [
                    1.0,
                    1.0,
                    1.0,
                    1.0
                  ],
                  "zoom": 1.0,
                  "round": 0.0,
                  "border_size": 0.0,
                  "border_color": [
                    0.0,
                    0.0,
                    0.0,
                    1.0
                  ],
                  "conditions": [],
                  "duration_bar": false,
                  "duration_text": false,
                  "stacks_text": false,
                  "size": [
                    276.0,
                    76.0
                  ]
                }
              ]
            },
            {
              "enabled": true,
              "name": "duration",
              "anchor": "Parent",
              "pos": [
                0.0,
                0.0
              ],
              "opacity": 1.0,
              "trigger": {
                "source": "Inherit",
                "threshold": {
                  "threshold_type": "Present",
                  "amount_type": "Intensity"
                }
              },
              "filter": {
                "player": {
                  "combat": null,
                  "specs": [],
                  "weapons": [],
                  "traits": [],
                  "mounts": []
                },
                "map": {
                  "category": [],
                  "whitelist": true,
                  "ids": []
                }
              },
              "animation": null,
              "type": "Bar",
              "progress_kind": "Duration",
              "max": 25.0,
              "lower_bound": 0.0,
              "upper_bound": 1.0,
              "fill": [
                1.0,
                0.9999925,
                0.99999,
                1.0
              ],
              "background": [
                0.0,
                0.0,
                0.0,
                0.497006
              ],
              "border_size": 1.0,
              "border_color": [
                0.0,
                0.0,
                0.0,
                1.0
              ],
              "tick_size": 1.0,
              "tick_color": [
                0.0,
                0.0,
                0.0,
                1.0
              ],
              "conditions": [],
              "size": [
                259.0,
                10.0
              ],
              "align": "Left",
              "direction": "Right",
              "tick_unit": "Percent",
              "ticks": []
            }
          ]
        }
      ]
    },
    {
      "enabled": true,
      "name": "bladesworn",
      "anchor": "Parent",
      "pos": [
        0.0,
        -119.0
      ],
      "opacity": 1.0,
      "trigger": {
        "source": "Inherit",
        "threshold": {
          "threshold_type": "Always",
          "amount_type": "Intensity"
        }
      },
      "filter": {
        "player": {
          "combat": null,
          "specs": [
            "Bladesworn"
          ],
          "weapons": [],
          "traits": [],
          "mounts": []
        },
        "map": {
          "category": [],
          "whitelist": true,
          "ids": []
        }
      },
      "animation": null,
      "type": "Group",
      "members": [
        {
          "enabled": true,
          "name": "positive-flow",
          "anchor": "Parent",
          "pos": [
            -272.0,
            -8.0
          ],
          "opacity": 1.0,
          "trigger": {
            "source": {
              "Buff": [
                62836
              ]
            },
            "threshold": {
              "threshold_type": "Always",
              "amount_type": "Intensity"
            }
          },
          "filter": {
            "player": {
              "combat": null,
              "specs": [],
              "weapons": [],
              "traits": [],
              "mounts": []
            },
            "map": {
              "category": [],
              "whitelist": true,
              "ids": []
            }
          },
          "animation": null,
          "type": "Group",
          "members": [
            {
              "enabled": true,
              "name": "1",
              "anchor": "Parent",
              "pos": [
                0.0,
                0.0
              ],
              "opacity": 1.0,
              "trigger": {
                "source": "Inherit",
                "threshold": {
                  "threshold_type": {
                    "Above": 1.0
                  },
                  "amount_type": "Intensity"
                }
              },
              "filter": {
                "player": {
                  "combat": null,
                  "specs": [],
                  "weapons": [],
                  "traits": [],
                  "mounts": []
                },
                "map": {
                  "category": [],
                  "whitelist": true,
                  "ids": []
                }
              },
              "animation": null,
              "type": "Icon",
              "icon": {
                "File": "instinct\\bladesworn\\positive-flow.png"
              },
              "tint": [
                1.0,
                1.0,
                1.0,
                1.0
              ],
              "zoom": 1.0,
              "round": 0.0,
              "border_size": 0.0,
              "border_color": [
                0.0,
                0.0,
                0.0,
                1.0
              ],
              "conditions": [],
              "duration_bar": false,
              "duration_text": false,
              "stacks_text": false,
              "size": [
                12.0,
                20.0
              ]
            },
            {
              "enabled": true,
              "name": "2",
              "anchor": "Parent",
              "pos": [
                14.0,
                0.0
              ],
              "opacity": 1.0,
              "trigger": {
                "source": "Inherit",
                "threshold": {
                  "threshold_type": {
                    "Above": 2.0
                  },
                  "amount_type": "Intensity"
                }
              },
              "filter": {
                "player": {
                  "combat": null,
                  "specs": [],
                  "weapons": [],
                  "traits": [],
                  "mounts": []
                },
                "map": {
                  "category": [],
                  "whitelist": true,
                  "ids": []
                }
              },
              "animation": null,
              "type": "Icon",
              "icon": {
                "File": "instinct\\bladesworn\\positive-flow.png"
              },
              "tint": [
                1.0,
                1.0,
                1.0,
                1.0
              ],
              "zoom": 1.0,
              "round": 0.0,
              "border_size": 0.0,
              "border_color": [
                0.0,
                0.0,
                0.0,
                1.0
              ],
              "conditions": [],
              "duration_bar": false,
              "duration_text": false,
              "stacks_text": false,
              "size": [
                12.0,
                20.0
              ]
            },
            {
              "enabled": true,
              "name": "3",
              "anchor": "Parent",
              "pos": [
                28.0,
                0.0
              ],
              "opacity": 1.0,
              "trigger": {
                "source": "Inherit",
                "threshold": {
                  "threshold_type": {
                    "Above": 3.0
                  },
                  "amount_type": "Intensity"
                }
              },
              "filter": {
                "player": {
                  "combat": null,
                  "specs": [],
                  "weapons": [],
                  "traits": [],
                  "mounts": []
                },
                "map": {
                  "category": [],
                  "whitelist": true,
                  "ids": []
                }
              },
              "animation": null,
              "type": "Icon",
              "icon": {
                "File": "instinct\\bladesworn\\positive-flow.png"
              },
              "tint": [
                1.0,
                1.0,
                1.0,
                1.0
              ],
              "zoom": 1.0,
              "round": 0.0,
              "border_size": 0.0,
              "border_color": [
                0.0,
                0.0,
                0.0,
                1.0
              ],
              "conditions": [],
              "duration_bar": false,
              "duration_text": false,
              "stacks_text": false,
              "size": [
                12.0,
                20.0
              ]
            },
            {
              "enabled": true,
              "name": "4",
              "anchor": "Parent",
              "pos": [
                42.0,
                0.0
              ],
              "opacity": 1.0,
              "trigger": {
                "source": "Inherit",
                "threshold": {
                  "threshold_type": {
                    "Above": 4.0
                  },
                  "amount_type": "Intensity"
                }
              },
              "filter": {
                "player": {
                  "combat": null,
                  "specs": [],
                  "weapons": [],
                  "traits": [],
                  "mounts": []
                },
                "map": {
                  "category": [],
                  "whitelist": true,
                  "ids": []
                }
              },
              "animation": null,
              "type": "Icon",
              "icon": {
                "File": "instinct\\bladesworn\\positive-flow.png"
              },
              "tint": [
                1.0,
                1.0,
                1.0,
                1.0
              ],
              "zoom": 1.0,
              "round": 0.0,
              "border_size": 0.0,
              "border_color": [
                0.0,
                0.0,
                0.0,
                1.0
              ],
              "conditions": [],
              "duration_bar": false,
              "duration_text": false,
              "stacks_text": false,
              "size": [
                12.0,
                20.0
              ]
            },
            {
              "enabled": true,
              "name": "5",
              "anchor": "Parent",
              "pos": [
                56.0,
                0.0
              ],
              "opacity": 1.0,
              "trigger": {
                "source": "Inherit",
                "threshold": {
                  "threshold_type": {
                    "Above": 5.0
                  },
                  "amount_type": "Intensity"
                }
              },
              "filter": {
                "player": {
                  "combat": null,
                  "specs": [],
                  "weapons": [],
                  "traits": [],
                  "mounts": []
                },
                "map": {
                  "category": [],
                  "whitelist": true,
                  "ids": []
                }
              },
              "animation": null,
              "type": "Icon",
              "icon": {
                "File": "instinct\\bladesworn\\positive-flow.png"
              },
              "tint": [
                1.0,
                1.0,
                1.0,
                1.0
              ],
              "zoom": 1.0,
              "round": 0.0,
              "border_size": 0.0,
              "border_color": [
                0.0,
                0.0,
                0.0,
                1.0
              ],
              "conditions": [],
              "duration_bar": false,
              "duration_text": false,
              "stacks_text": false,
              "size": [
                12.0,
                20.0
              ]
            }
          ]
        }
      ]
    },
    {
      "enabled": true,
      "name": "harbinger",
      "anchor": "Parent",
      "pos": [
        0.0,
        0.0
      ],
      "opacity": 1.0,
      "trigger": {
        "source": "Inherit",
        "threshold": {
          "threshold_type": "Always",
          "amount_type": "Intensity"
        }
      },
      "filter": {
        "player": {
          "combat": null,
          "specs": [
            "Harbinger"
          ],
          "weapons": [],
          "traits": [],
          "mounts": []
        },
        "map": {
          "category": [],
          "whitelist": true,
          "ids": []
        }
      },
      "animation": null,
      "type": "Group",
      "members": [
        {
          "enabled": true,
          "name": "blight",
          "anchor": "Parent",
          "pos": [
            -260.0,
            -186.0
          ],
          "opacity": 1.0,
          "trigger": {
            "source": {
              "Buff": [
                62653
              ]
            },
            "threshold": {
              "threshold_type": "Always",
              "amount_type": "Intensity"
            }
          },
          "filter": {
            "player": {
              "combat": null,
              "specs": [],
              "weapons": [],
              "traits": [],
              "mounts": []
            },
            "map": {
              "category": [],
              "whitelist": true,
              "ids": []
            }
          },
          "animation": null,
          "type": "Group",
          "members": [
            {
              "enabled": true,
              "name": "main",
              "anchor": "Parent",
              "pos": [
                49.0,
                -2.0
              ],
              "opacity": 1.0,
              "trigger": {
                "source": "Inherit",
                "threshold": {
                  "threshold_type": "Always",
                  "amount_type": "Intensity"
                }
              },
              "filter": {
                "player": {
                  "combat": null,
                  "specs": [],
                  "weapons": [],
                  "traits": [],
                  "mounts": []
                },
                "map": {
                  "category": [],
                  "whitelist": true,
                  "ids": []
                }
              },
              "animation": null,
              "type": "Icon",
              "icon": {
                "File": "instinct\\harbinger\\main.png"
              },
              "tint": [
                1.0,
                1.0,
                1.0,
                1.0
              ],
              "zoom": 1.0,
              "round": 0.0,
              "border_size": 0.0,
              "border_color": [
                0.0,
                0.0,
                0.0,
                1.0
              ],
              "conditions": [],
              "duration_bar": false,
              "duration_text": false,
              "stacks_text": false,
              "size": [
                292.0,
                120.0
              ]
            },
            {
              "enabled": true,
              "name": "needle-below-10",
              "anchor": "Parent",
              "pos": [
                49.0,
                -2.0
              ],
              "opacity": 1.0,
              "trigger": {
                "source": "Inherit",
                "threshold": {
                  "threshold_type": {
                    "Below": 9.0
                  },
                  "amount_type": "Intensity"
                }
              },
              "filter": {
                "player": {
                  "combat": null,
                  "specs": [],
                  "weapons": [],
                  "traits": [],
                  "mounts": []
                },
                "map": {
                  "category": [],
                  "whitelist": true,
                  "ids": []
                }
              },
              "animation": null,
              "type": "Icon",
              "icon": {
                "File": "instinct\\harbinger\\needle-1.png"
              },
              "tint": [
                1.0,
                1.0,
                1.0,
                1.0
              ],
              "zoom": 1.0,
              "round": 0.0,
              "border_size": 0.0,
              "border_color": [
                0.0,
                0.0,
                0.0,
                1.0
              ],
              "conditions": [],
              "duration_bar": false,
              "duration_text": false,
              "stacks_text": false,
              "size": [
                292.0,
                120.0
              ]
            },
            {
              "enabled": true,
              "name": "needle-10-up",
              "anchor": "Parent",
              "pos": [
                49.0,
                -2.0
              ],
              "opacity": 1.0,
              "trigger": {
                "source": "Inherit",
                "threshold": {
                  "threshold_type": {
                    "Between": [
                      10.0,
                      24.0
                    ]
                  },
                  "amount_type": "Intensity"
                }
              },
              "filter": {
                "player": {
                  "combat": null,
                  "specs": [],
                  "weapons": [],
                  "traits": [],
                  "mounts": []
                },
                "map": {
                  "category": [],
                  "whitelist": true,
                  "ids": []
                }
              },
              "animation": null,
              "type": "Icon",
              "icon": {
                "File": "instinct\\harbinger\\needle-2.png"
              },
              "tint": [
                1.0,
                1.0,
                1.0,
                1.0
              ],
              "zoom": 1.0,
              "round": 0.0,
              "border_size": 0.0,
              "border_color": [
                0.0,
                0.0,
                0.0,
                1.0
              ],
              "conditions": [],
              "duration_bar": false,
              "duration_text": false,
              "stacks_text": false,
              "size": [
                292.0,
                120.0
              ]
            },
            {
              "enabled": true,
              "name": "needle-25",
              "anchor": "Parent",
              "pos": [
                49.0,
                -2.0
              ],
              "opacity": 1.0,
              "trigger": {
                "source": "Inherit",
                "threshold": {
                  "threshold_type": {
                    "Exact": 25.0
                  },
                  "amount_type": "Intensity"
                }
              },
              "filter": {
                "player": {
                  "combat": null,
                  "specs": [],
                  "weapons": [],
                  "traits": [],
                  "mounts": []
                },
                "map": {
                  "category": [],
                  "whitelist": true,
                  "ids": []
                }
              },
              "animation": null,
              "type": "Icon",
              "icon": {
                "File": "instinct\\harbinger\\needle-3.png"
              },
              "tint": [
                1.0,
                1.0,
                1.0,
                1.0
              ],
              "zoom": 1.0,
              "round": 0.0,
              "border_size": 0.0,
              "border_color": [
                0.0,
                0.0,
                0.0,
                1.0
              ],
              "conditions": [],
              "duration_bar": false,
              "duration_text": false,
              "stacks_text": false,
              "size": [
                292.0,
                120.0
              ]
            },
            {
              "enabled": true,
              "name": "intensity",
              "anchor": "Parent",
              "pos": [
                27.0,
                2.0
              ],
              "opacity": 1.0,
              "trigger": {
                "source": "Inherit",
                "threshold": {
                  "threshold_type": "Always",
                  "amount_type": "Intensity"
                }
              },
              "filter": {
                "player": {
                  "combat": null,
                  "specs": [],
                  "weapons": [],
                  "traits": [],
                  "mounts": []
                },
                "map": {
                  "category": [],
                  "whitelist": true,
                  "ids": []
                }
              },
              "animation": null,
              "type": "Bar",
              "progress_kind": "Intensity",
              "max": 25.0,
              "lower_bound": 0.0,
              "upper_bound": 1.0,
              "fill": [
                0.46141818,
                0.9161677,
                0.21944137,
                1.0
              ],
              "background": [
                0.08655741,
                0.8502994,
                0.70275825,
                0.0
              ],
              "border_size": 0.0,
              "border_color": [
                0.0,
                0.0,
                0.0,
                1.0
              ],
              "tick_size": 1.0,
              "tick_color": [
                0.0,
                0.0,
                0.0,
                1.0
              ],
              "conditions": [],
              "size": [
                125.0,
                12.0
              ],
              "align": "Center",
              "direction": "Right",
              "tick_unit": "Percent",
              "ticks": []
            },
            {
              "enabled": true,
              "name": "duration",
              "anchor": "Parent",
              "pos": [
                -81.0,
                -21.0
              ],
              "opacity": 1.0,
              "trigger": {
                "source": "Inherit",
                "threshold": {
                  "threshold_type": "Present",
                  "amount_type": "Intensity"
                }
              },
              "filter": {
                "player": {
                  "combat": null,
                  "specs": [],
                  "weapons": [],
                  "traits": [],
                  "mounts": []
                },
                "map": {
                  "category": [],
                  "whitelist": true,
                  "ids": []
                }
              },
              "animation": null,
              "type": "Text",
              "text": "%c",
              "font": null,
              "align": "Center",
              "scale": 1.0,
              "color": [
                0.000001,
                9.9999e-7,
                9.9999e-7,
                1.0
              ],
              "decoration": "None",
              "conditions": []
            },
            {
              "enabled": true,
              "name": "bubbles-a",
              "anchor": "Parent",
              "pos": [
                49.0,
                -2.0
              ],
              "opacity": 1.0,
              "trigger": {
                "source": "Inherit",
                "threshold": {
                  "threshold_type": "Present",
                  "amount_type": "Intensity"
                }
              },
              "filter": {
                "player": {
                  "combat": null,
                  "specs": [],
                  "weapons": [],
                  "traits": [],
                  "mounts": []
                },
                "map": {
                  "category": [],
                  "whitelist": true,
                  "ids": []
                }
              },
              "animation": {
                "kind": "Pulse",
                "period": 1000
              },
              "type": "Icon",
              "icon": {
                "File": "instinct\\harbinger\\bubbles-a.png"
              },
              "tint": [
                1.0,
                1.0,
                1.0,
                1.0
              ],
              "zoom": 1.0,
              "round": 0.0,
              "border_size": 0.0,
              "border_color": [
                0.0,
                0.0,
                0.0,
                1.0
              ],
              "conditions": [],
              "duration_bar": false,
              "duration_text": false,
              "stacks_text": false,
              "size": [
                292.0,
                120.0
              ]
            },
            {
              "enabled": true,
              "name": "bubbles-b",
              "anchor": "Parent",
              "pos": [
                49.0,
                -2.0
              ],
              "opacity": 1.0,
              "trigger": {
                "source": "Inherit",
                "threshold": {
                  "threshold_type": "Present",
                  "amount_type": "Intensity"
                }
              },
              "filter": {
                "player": {
                  "combat": null,
                  "specs": [],
                  "weapons": [],
                  "traits": [],
                  "mounts": []
                },
                "map": {
                  "category": [],
                  "whitelist": true,
                  "ids": []
                }
              },
              "animation": {
                "kind": "Pulse",
                "period": 1750
              },
              "type": "Icon",
              "icon": {
                "File": "instinct\\harbinger\\bubbles-b.png"
              },
              "tint": [
                1.0,
                1.0,
                1.0,
                1.0
              ],
              "zoom": 1.0,
              "round": 0.0,
              "border_size": 0.0,
              "border_color": [
                0.0,
                0.0,
                0.0,
                1.0
              ],
              "conditions": [],
              "duration_bar": false,
              "duration_text": false,
              "stacks_text": false,
              "size": [
                292.0,
                120.0
              ]
            },
            {
              "enabled": true,
              "name": "spikes-a",
              "anchor": "Parent",
              "pos": [
                49.0,
                -2.0
              ],
              "opacity": 1.0,
              "trigger": {
                "source": "Inherit",
                "threshold": {
                  "threshold_type": {
                    "Exact": 25.0
                  },
                  "amount_type": "Intensity"
                }
              },
              "filter": {
                "player": {
                  "combat": null,
                  "specs": [],
                  "weapons": [],
                  "traits": [],
                  "mounts": []
                },
                "map": {
                  "category": [],
                  "whitelist": true,
                  "ids": []
                }
              },
              "animation": {
                "kind": "Pulse",
                "period": 1000
              },
              "type": "Icon",
              "icon": {
                "File": "instinct\\harbinger\\spikes-a.png"
              },
              "tint": [
                1.0,
                1.0,
                1.0,
                1.0
              ],
              "zoom": 1.0,
              "round": 0.0,
              "border_size": 0.0,
              "border_color": [
                0.0,
                0.0,
                0.0,
                1.0
              ],
              "conditions": [],
              "duration_bar": false,
              "duration_text": false,
              "stacks_text": false,
              "size": [
                292.0,
                120.0
              ]
            },
            {
              "enabled": true,
              "name": "spikes-b",
              "anchor": "Parent",
              "pos": [
                49.0,
                -2.0
              ],
              "opacity": 1.0,
              "trigger": {
                "source": "Inherit",
                "threshold": {
                  "threshold_type": {
                    "Exact": 25.0
                  },
                  "amount_type": "Intensity"
                }
              },
              "filter": {
                "player": {
                  "combat": null,
                  "specs": [],
                  "weapons": [],
                  "traits": [],
                  "mounts": []
                },
                "map": {
                  "category": [],
                  "whitelist": true,
                  "ids": []
                }
              },
              "animation": {
                "kind": "Pulse",
                "period": 1750
              },
              "type": "Icon",
              "icon": {
                "File": "instinct\\harbinger\\spikes-b.png"
              },
              "tint": [
                1.0,
                1.0,
                1.0,
                1.0
              ],
              "zoom": 1.0,
              "round": 0.0,
              "border_size": 0.0,
              "border_color": [
                0.0,
                0.0,
                0.0,
                1.0
              ],
              "conditions": [],
              "duration_bar": false,
              "duration_text": false,
              "stacks_text": false,
              "size": [
                292.0,
                120.0
              ]
            },
            {
              "enabled": true,
              "name": "glass",
              "anchor": "Parent",
              "pos": [
                49.0,
                -2.0
              ],
              "opacity": 1.0,
              "trigger": {
                "source": "Inherit",
                "threshold": {
                  "threshold_type": "Always",
                  "amount_type": "Intensity"
                }
              },
              "filter": {
                "player": {
                  "combat": null,
                  "specs": [],
                  "weapons": [],
                  "traits": [],
                  "mounts": []
                },
                "map": {
                  "category": [],
                  "whitelist": true,
                  "ids": []
                }
              },
              "animation": null,
              "type": "Icon",
              "icon": {
                "File": "instinct\\harbinger\\glass.png"
              },
              "tint": [
                1.0,
                1.0,
                1.0,
                1.0
              ],
              "zoom": 1.0,
              "round": 0.0,
              "border_size": 0.0,
              "border_color": [
                0.0,
                0.0,
                0.0,
                1.0
              ],
              "conditions": [],
              "duration_bar": false,
              "duration_text": false,
              "stacks_text": false,
              "size": [
                292.0,
                120.0
              ]
            },
            {
              "enabled": true,
              "name": "glass-cracks",
              "anchor": "Parent",
              "pos": [
                49.0,
                -2.0
              ],
              "opacity": 1.0,
              "trigger": {
                "source": "Health",
                "threshold": {
                  "threshold_type": {
                    "Below": 50.0
                  },
                  "amount_type": "Percent"
                }
              },
              "filter": {
                "player": {
                  "combat": null,
                  "specs": [],
                  "weapons": [],
                  "traits": [],
                  "mounts": []
                },
                "map": {
                  "category": [],
                  "whitelist": true,
                  "ids": []
                }
              },
              "animation": null,
              "type": "Icon",
              "icon": {
                "File": "instinct\\harbinger\\glass-cracks.png"
              },
              "tint": [
                1.0,
                1.0,
                1.0,
                1.0
              ],
              "zoom": 1.0,
              "round": 0.0,
              "border_size": 0.0,
              "border_color": [
                0.0,
                0.0,
                0.0,
                1.0
              ],
              "conditions": [],
              "duration_bar": false,
              "duration_text": false,
              "stacks_text": false,
              "size": [
                292.0,
                120.0
              ]
            },
            {
              "enabled": true,
              "name": "glow",
              "anchor": "Parent",
              "pos": [
                49.0,
                -2.0
              ],
              "opacity": 1.0,
              "trigger": {
                "source": "Inherit",
                "threshold": {
                  "threshold_type": {
                    "Above": 25.0
                  },
                  "amount_type": "Intensity"
                }
              },
              "filter": {
                "player": {
                  "combat": null,
                  "specs": [],
                  "weapons": [],
                  "traits": [],
                  "mounts": []
                },
                "map": {
                  "category": [],
                  "whitelist": true,
                  "ids": []
                }
              },
              "animation": {
                "kind": "Pulse",
                "period": 4000
              },
              "type": "Icon",
              "icon": {
                "File": "instinct\\harbinger\\glow.png"
              },
              "tint": [
                1.0,
                1.0,
                1.0,
                1.0
              ],
              "zoom": 1.0,
              "round": 0.0,
              "border_size": 0.0,
              "border_color": [
                0.0,
                0.0,
                0.0,
                1.0
              ],
              "conditions": [],
              "duration_bar": false,
              "duration_text": false,
              "stacks_text": false,
              "size": [
                292.0,
                120.0
              ]
            }
          ]
        }
      ]
    },
    {
      "enabled": true,
      "name": "untamed",
      "anchor": "Parent",
      "pos": [
        0.0,
        0.0
      ],
      "opacity": 1.0,
      "trigger": {
        "source": "Inherit",
        "threshold": {
          "threshold_type": "Always",
          "amount_type": "Intensity"
        }
      },
      "filter": {
        "player": {
          "combat": null,
          "specs": [
            "Untamed"
          ],
          "weapons": [],
          "traits": [],
          "mounts": []
        },
        "map": {
          "category": [],
          "whitelist": true,
          "ids": []
        }
      },
      "animation": null,
      "type": "Group",
      "members": [
        {
          "enabled": true,
          "name": "unleashed-power",
          "anchor": "Parent",
          "pos": [
            0.0,
            -241.0
          ],
          "opacity": 1.0,
          "trigger": {
            "source": {
              "Buff": [
                63404
              ]
            },
            "threshold": {
              "threshold_type": "Always",
              "amount_type": "Intensity"
            }
          },
          "filter": {
            "player": {
              "combat": null,
              "specs": [],
              "weapons": [],
              "traits": [],
              "mounts": []
            },
            "map": {
              "category": [],
              "whitelist": true,
              "ids": []
            }
          },
          "animation": null,
          "type": "Group",
          "members": [
            {
              "enabled": true,
              "name": "missing",
              "anchor": "Parent",
              "pos": [
                0.0,
                0.0
              ],
              "opacity": 1.0,
              "trigger": {
                "source": "Inherit",
                "threshold": {
                  "threshold_type": "Missing",
                  "amount_type": "Intensity"
                }
              },
              "filter": {
                "player": {
                  "combat": null,
                  "specs": [],
                  "weapons": [],
                  "traits": [],
                  "mounts": []
                },
                "map": {
                  "category": [],
                  "whitelist": true,
                  "ids": []
                }
              },
              "animation": null,
              "type": "Group",
              "members": [
                {
                  "enabled": true,
                  "name": "bg",
                  "anchor": "Parent",
                  "pos": [
                    0.0,
                    0.0
                  ],
                  "opacity": 1.0,
                  "trigger": {
                    "source": "Inherit",
                    "threshold": {
                      "threshold_type": "Missing",
                      "amount_type": "Intensity"
                    }
                  },
                  "filter": {
                    "player": {
                      "combat": null,
                      "specs": [],
                      "weapons": [],
                      "traits": [],
                      "mounts": []
                    },
                    "map": {
                      "category": [],
                      "whitelist": true,
                      "ids": []
                    }
                  },
                  "animation": null,
                  "type": "Icon",
                  "icon": {
                    "File": "instinct\\untamed\\bg-b.png"
                  },
                  "tint": [
                    1.0,
                    1.0,
                    1.0,
                    1.0
                  ],
                  "zoom": 1.0,
                  "round": 0.0,
                  "border_size": 0.0,
                  "border_color": [
                    0.0,
                    0.0,
                    0.0,
                    1.0
                  ],
                  "conditions": [],
                  "duration_bar": false,
                  "duration_text": false,
                  "stacks_text": false,
                  "size": [
                    124.0,
                    124.0
                  ]
                },
                {
                  "enabled": true,
                  "name": "mask-lines",
                  "anchor": "Parent",
                  "pos": [
                    0.0,
                    0.0
                  ],
                  "opacity": 1.0,
                  "trigger": {
                    "source": "Inherit",
                    "threshold": {
                      "threshold_type": "Missing",
                      "amount_type": "Intensity"
                    }
                  },
                  "filter": {
                    "player": {
                      "combat": null,
                      "specs": [],
                      "weapons": [],
                      "traits": [],
                      "mounts": []
                    },
                    "map": {
                      "category": [],
                      "whitelist": true,
                      "ids": []
                    }
                  },
                  "animation": null,
                  "type": "Icon",
                  "icon": {
                    "File": "instinct\\untamed\\mask-lines.png"
                  },
                  "tint": [
                    1.0,
                    1.0,
                    1.0,
                    1.0
                  ],
                  "zoom": 1.0,
                  "round": 0.0,
                  "border_size": 0.0,
                  "border_color": [
                    0.0,
                    0.0,
                    0.0,
                    1.0
                  ],
                  "conditions": [],
                  "duration_bar": false,
                  "duration_text": false,
                  "stacks_text": false,
                  "size": [
                    124.0,
                    124.0
                  ]
                }
              ]
            },
            {
              "enabled": false,
              "name": "present-ooc",
              "anchor": "Parent",
              "pos": [
                0.0,
                0.0
              ],
              "opacity": 1.0,
              "trigger": {
                "source": "Inherit",
                "threshold": {
                  "threshold_type": "Present",
                  "amount_type": "Intensity"
                }
              },
              "filter": {
                "player": {
                  "combat": false,
                  "specs": [],
                  "weapons": [],
                  "traits": [],
                  "mounts": []
                },
                "map": {
                  "category": [],
                  "whitelist": true,
                  "ids": []
                }
              },
              "animation": null,
              "type": "Group",
              "members": [
                {
                  "enabled": true,
                  "name": "bg",
                  "anchor": "Parent",
                  "pos": [
                    0.0,
                    0.0
                  ],
                  "opacity": 1.0,
                  "trigger": {
                    "source": "Inherit",
                    "threshold": {
                      "threshold_type": "Always",
                      "amount_type": "Intensity"
                    }
                  },
                  "filter": {
                    "player": {
                      "combat": null,
                      "specs": [],
                      "weapons": [],
                      "traits": [],
                      "mounts": []
                    },
                    "map": {
                      "category": [],
                      "whitelist": true,
                      "ids": []
                    }
                  },
                  "animation": null,
                  "type": "Icon",
                  "icon": {
                    "File": "instinct\\untamed\\bg-b.png"
                  },
                  "tint": [
                    1.0,
                    1.0,
                    1.0,
                    1.0
                  ],
                  "zoom": 1.0,
                  "round": 0.0,
                  "border_size": 0.0,
                  "border_color": [
                    0.0,
                    0.0,
                    0.0,
                    1.0
                  ],
                  "conditions": [],
                  "duration_bar": false,
                  "duration_text": false,
                  "stacks_text": false,
                  "size": [
                    124.0,
                    124.0
                  ]
                },
                {
                  "enabled": true,
                  "name": "mask-lines",
                  "anchor": "Parent",
                  "pos": [
                    0.0,
                    0.0
                  ],
                  "opacity": 1.0,
                  "trigger": {
                    "source": "Inherit",
                    "threshold": {
                      "threshold_type": "Always",
                      "amount_type": "Intensity"
                    }
                  },
                  "filter": {
                    "player": {
                      "combat": null,
                      "specs": [],
                      "weapons": [],
                      "traits": [],
                      "mounts": []
                    },
                    "map": {
                      "category": [],
                      "whitelist": true,
                      "ids": []
                    }
                  },
                  "animation": null,
                  "type": "Icon",
                  "icon": {
                    "File": "instinct\\untamed\\mask-lines.png"
                  },
                  "tint": [
                    1.0,
                    1.0,
                    1.0,
                    1.0
                  ],
                  "zoom": 1.0,
                  "round": 0.0,
                  "border_size": 0.0,
                  "border_color": [
                    0.0,
                    0.0,
                    0.0,
                    1.0
                  ],
                  "conditions": [],
                  "duration_bar": false,
                  "duration_text": false,
                  "stacks_text": false,
                  "size": [
                    124.0,
                    124.0
                  ]
                }
              ]
            },
            {
              "enabled": true,
              "name": "present",
              "anchor": "Parent",
              "pos": [
                0.0,
                0.0
              ],
              "opacity": 1.0,
              "trigger": {
                "source": "Inherit",
                "threshold": {
                  "threshold_type": "Present",
                  "amount_type": "Intensity"
                }
              },
              "filter": {
                "player": {
                  "combat": null,
                  "specs": [],
                  "weapons": [],
                  "traits": [],
                  "mounts": []
                },
                "map": {
                  "category": [],
                  "whitelist": true,
                  "ids": []
                }
              },
              "animation": null,
              "type": "Group",
              "members": [
                {
                  "enabled": true,
                  "name": "bg",
                  "anchor": "Parent",
                  "pos": [
                    0.0,
                    0.0
                  ],
                  "opacity": 1.0,
                  "trigger": {
                    "source": "Inherit",
                    "threshold": {
                      "threshold_type": "Always",
                      "amount_type": "Intensity"
                    }
                  },
                  "filter": {
                    "player": {
                      "combat": null,
                      "specs": [],
                      "weapons": [],
                      "traits": [],
                      "mounts": []
                    },
                    "map": {
                      "category": [],
                      "whitelist": true,
                      "ids": []
                    }
                  },
                  "animation": null,
                  "type": "Icon",
                  "icon": {
                    "File": "instinct\\untamed\\glow-b.png"
                  },
                  "tint": [
                    1.0,
                    1.0,
                    1.0,
                    1.0
                  ],
                  "zoom": 1.0,
                  "round": 0.0,
                  "border_size": 0.0,
                  "border_color": [
                    0.0,
                    0.0,
                    0.0,
                    1.0
                  ],
                  "conditions": [],
                  "duration_bar": false,
                  "duration_text": false,
                  "stacks_text": false,
                  "size": [
                    124.0,
                    124.0
                  ]
                },
                {
                  "enabled": true,
                  "name": "shimmer",
                  "anchor": "Parent",
                  "pos": [
                    0.0,
                    0.0
                  ],
                  "opacity": 1.0,
                  "trigger": {
                    "source": "Inherit",
                    "threshold": {
                      "threshold_type": "Always",
                      "amount_type": "Intensity"
                    }
                  },
                  "filter": {
                    "player": {
                      "combat": null,
                      "specs": [],
                      "weapons": [],
                      "traits": [],
                      "mounts": []
                    },
                    "map": {
                      "category": [],
                      "whitelist": true,
                      "ids": []
                    }
                  },
                  "animation": {
                    "kind": "Pulse",
                    "period": 2000
                  },
                  "type": "Icon",
                  "icon": {
                    "File": "instinct\\untamed\\shimmer.png"
                  },
                  "tint": [
                    1.0,
                    1.0,
                    1.0,
                    1.0
                  ],
                  "zoom": 1.0,
                  "round": 0.0,
                  "border_size": 0.0,
                  "border_color": [
                    0.0,
                    0.0,
                    0.0,
                    1.0
                  ],
                  "conditions": [],
                  "duration_bar": false,
                  "duration_text": false,
                  "stacks_text": false,
                  "size": [
                    124.0,
                    124.0
                  ]
                },
                {
                  "enabled": true,
                  "name": "mask",
                  "anchor": "Parent",
                  "pos": [
                    0.0,
                    0.0
                  ],
                  "opacity": 1.0,
                  "trigger": {
                    "source": "Inherit",
                    "threshold": {
                      "threshold_type": "Always",
                      "amount_type": "Intensity"
                    }
                  },
                  "filter": {
                    "player": {
                      "combat": null,
                      "specs": [],
                      "weapons": [],
                      "traits": [],
                      "mounts": []
                    },
                    "map": {
                      "category": [],
                      "whitelist": true,
                      "ids": []
                    }
                  },
                  "animation": null,
                  "type": "Icon",
                  "icon": {
                    "File": "instinct\\untamed\\mask-fill-blue.png"
                  },
                  "tint": [
                    1.0,
                    1.0,
                    1.0,
                    1.0
                  ],
                  "zoom": 1.0,
                  "round": 0.0,
                  "border_size": 0.0,
                  "border_color": [
                    0.0,
                    0.0,
                    0.0,
                    1.0
                  ],
                  "conditions": [],
                  "duration_bar": false,
                  "duration_text": false,
                  "stacks_text": false,
                  "size": [
                    124.0,
                    124.0
                  ]
                },
                {
                  "enabled": true,
                  "name": "motes-a",
                  "anchor": "Parent",
                  "pos": [
                    0.0,
                    0.0
                  ],
                  "opacity": 1.0,
                  "trigger": {
                    "source": "Inherit",
                    "threshold": {
                      "threshold_type": "Always",
                      "amount_type": "Intensity"
                    }
                  },
                  "filter": {
                    "player": {
                      "combat": null,
                      "specs": [],
                      "weapons": [],
                      "traits": [],
                      "mounts": []
                    },
                    "map": {
                      "category": [],
                      "whitelist": true,
                      "ids": []
                    }
                  },
                  "animation": {
                    "kind": "Pulse",
                    "period": 1750
                  },
                  "type": "Icon",
                  "icon": {
                    "File": "instinct\\untamed\\motes-a.png"
                  },
                  "tint": [
                    1.0,
                    1.0,
                    1.0,
                    1.0
                  ],
                  "zoom": 1.0,
                  "round": 0.0,
                  "border_size": 0.0,
                  "border_color": [
                    0.0,
                    0.0,
                    0.0,
                    1.0
                  ],
                  "conditions": [],
                  "duration_bar": false,
                  "duration_text": false,
                  "stacks_text": false,
                  "size": [
                    124.0,
                    124.0
                  ]
                },
                {
                  "enabled": true,
                  "name": "motes-b",
                  "anchor": "Parent",
                  "pos": [
                    0.0,
                    0.0
                  ],
                  "opacity": 1.0,
                  "trigger": {
                    "source": "Inherit",
                    "threshold": {
                      "threshold_type": "Always",
                      "amount_type": "Intensity"
                    }
                  },
                  "filter": {
                    "player": {
                      "combat": null,
                      "specs": [],
                      "weapons": [],
                      "traits": [],
                      "mounts": []
                    },
                    "map": {
                      "category": [],
                      "whitelist": true,
                      "ids": []
                    }
                  },
                  "animation": {
                    "kind": "Pulse",
                    "period": 2250
                  },
                  "type": "Icon",
                  "icon": {
                    "File": "instinct\\untamed\\motes-b.png"
                  },
                  "tint": [
                    1.0,
                    1.0,
                    1.0,
                    1.0
                  ],
                  "zoom": 1.0,
                  "round": 0.0,
                  "border_size": 0.0,
                  "border_color": [
                    0.0,
                    0.0,
                    0.0,
                    1.0
                  ],
                  "conditions": [],
                  "duration_bar": false,
                  "duration_text": false,
                  "stacks_text": false,
                  "size": [
                    124.0,
                    124.0
                  ]
                }
              ]
            }
          ]
        }
      ]
    }
  ]
}